{"impl":"optimize","threads":1,"scale":10000,"distribution":"uniform","runs":1,"insert_ms":0.458084,"insert_std":0,"insert_ops_sec":21830057,"contains_ms":0.1415,"contains_std":0,"contains_ops_sec":70671378}
{"impl":"optimize","threads":2,"scale":10000,"distribution":"uniform","runs":1,"insert_ms":1.02046,"insert_std":0,"insert_ops_sec":9799511,"contains_ms":0.379584,"contains_std":0,"contains_ops_sec":26344629}
{"impl":"optimize","threads":4,"scale":10000,"distribution":"uniform","runs":1,"insert_ms":0.915084,"insert_std":0,"insert_ops_sec":10927958,"contains_ms":0.431458,"contains_std":0,"contains_ops_sec":23177226}
{"impl":"optimize","threads":8,"scale":10000,"distribution":"uniform","runs":1,"insert_ms":1.06621,"insert_std":0,"insert_ops_sec":9379024,"contains_ms":0.402084,"contains_std":0,"contains_ops_sec":24870425}
{"impl":"optimize","threads":16,"scale":10000,"distribution":"uniform","runs":1,"insert_ms":1.412,"insert_std":0,"insert_ops_sec":7082152,"contains_ms":0.349292,"contains_std":0,"contains_ops_sec":28629341}
{"impl":"optimize","threads":32,"scale":10000,"distribution":"uniform","runs":1,"insert_ms":2.14683,"insert_std":0,"insert_ops_sec":4658024,"contains_ms":1.54667,"contains_std":0,"contains_ops_sec":6465515}
{"impl":"optimize","threads":1,"scale":10000,"distribution":"gaussian","runs":1,"insert_ms":0.245792,"insert_std":0,"insert_ops_sec":40684806,"contains_ms":0.109792,"contains_std":0,"contains_ops_sec":91081317}
{"impl":"optimize","threads":2,"scale":10000,"distribution":"gaussian","runs":1,"insert_ms":0.862167,"insert_std":0,"insert_ops_sec":11598680,"contains_ms":0.355042,"contains_std":0,"contains_ops_sec":28165681}
{"impl":"optimize","threads":4,"scale":10000,"distribution":"gaussian","runs":1,"insert_ms":0.767625,"insert_std":0,"insert_ops_sec":13027194,"contains_ms":0.427,"contains_std":0,"contains_ops_sec":23419203}
{"impl":"optimize","threads":8,"scale":10000,"distribution":"gaussian","runs":1,"insert_ms":0.935459,"insert_std":0,"insert_ops_sec":10689939,"contains_ms":0.592833,"contains_std":0,"contains_ops_sec":16868156}
{"impl":"optimize","threads":16,"scale":10000,"distribution":"gaussian","runs":1,"insert_ms":1.31171,"insert_std":0,"insert_ops_sec":7623647,"contains_ms":0.564708,"contains_std":0,"contains_ops_sec":17708266}
{"impl":"optimize","threads":32,"scale":10000,"distribution":"gaussian","runs":1,"insert_ms":1.59888,"insert_std":0,"insert_ops_sec":6254397,"contains_ms":1.01887,"contains_std":0,"contains_ops_sec":9814746}
{"impl":"optimize","threads":1,"scale":10000,"distribution":"localized","runs":1,"insert_ms":0.19275,"insert_std":0,"insert_ops_sec":51880674,"contains_ms":0.109166,"contains_std":0,"contains_ops_sec":91603612}
{"impl":"optimize","threads":2,"scale":10000,"distribution":"localized","runs":1,"insert_ms":0.475833,"insert_std":0,"insert_ops_sec":21015776,"contains_ms":0.366625,"contains_std":0,"contains_ops_sec":27275826}
{"impl":"optimize","threads":4,"scale":10000,"distribution":"localized","runs":1,"insert_ms":0.517791,"insert_std":0,"insert_ops_sec":19312811,"contains_ms":0.394292,"contains_std":0,"contains_ops_sec":25361914}
{"impl":"optimize","threads":8,"scale":10000,"distribution":"localized","runs":1,"insert_ms":0.628,"insert_std":0,"insert_ops_sec":15923566,"contains_ms":0.503209,"contains_std":0,"contains_ops_sec":19872458}
{"impl":"optimize","threads":16,"scale":10000,"distribution":"localized","runs":1,"insert_ms":0.710834,"insert_std":0,"insert_ops_sec":14067982,"contains_ms":0.464667,"contains_std":0,"contains_ops_sec":21520788}
{"impl":"optimize","threads":32,"scale":10000,"distribution":"localized","runs":1,"insert_ms":1.07537,"insert_std":0,"insert_ops_sec":9299081,"contains_ms":0.546208,"contains_std":0,"contains_ops_sec":18308043}
